opensr_utils/__init__.py
opensr_utils/__main__.py
opensr_utils/cli.py
opensr_utils/pipeline.py
opensr_utils/data_utils/__init__.py
opensr_utils/data_utils/datamodule.py
opensr_utils/data_utils/reading_utils.py
opensr_utils/data_utils/result_analysis.py
opensr_utils/data_utils/transform_to_cog.py
opensr_utils/data_utils/writing_utils.py
opensr_utils/model_utils/__init__.py
opensr_utils/model_utils/get_models.py
opensr_utils/model_utils/prepare_model.py
opensr_utils-1.2.0.dist-info/licenses/LICENSE.md
opensr_utils-1.2.0.dist-info/METADATA
opensr_utils-1.2.0.dist-info/WHEEL
opensr_utils-1.2.0.dist-info/entry_points.txt
opensr_utils-1.2.0.dist-info/top_level.txt
opensr_utils-1.2.0.dist-info/RECORD
