Metadata-Version: 2.4
Name: opensr-utils
Version: 1.2.0
Summary: Utilities supporting the ESA opensr-model package for Super-Resolution of Senintel-2 Imagery
Home-page: https://opensr.eu/
Author: Simon Donike, Cesar Aybar, Luis Gomez Chova, Freddie Kalaitzis
Author-email: accounts@donike.net
License: MIT
Project-URL: Source Code, https://github.com/ESAopenSR/opensr-utils
License-File: LICENSE.md
Requires-Dist: numpy
Requires-Dist: einops
Requires-Dist: rasterio
Requires-Dist: tqdm
Requires-Dist: torch
Requires-Dist: scikit-image
Requires-Dist: torchvision
Requires-Dist: pytorch-lightning
Requires-Dist: xarray
Requires-Dist: matplotlib
Requires-Dist: omegaconf
Requires-Dist: requests
Dynamic: author
Dynamic: author-email
Dynamic: description
Dynamic: description-content-type
Dynamic: home-page
Dynamic: license
Dynamic: license-file
Dynamic: project-url
Dynamic: requires-dist
Dynamic: summary
